[0,[[[["EnterPostproc",[],[],[]]],[]],[1.8015524230931311608e-05],{"arch":"sm_70","keys":["cuda","gpu"],"kind":"cuda","max_num_threads":1024,"max_shared_memory_per_block":65536,"max_threads_per_block":1024,"tag":"","thread_warp_size":32},[["TENSOR","float32",[1024,1024]],["TENSOR","float32",[512,2,1024]],["TENSOR","int32",[512,2]]]]]
[0,[[[["EnterPostproc",[],[],[]]],[]],[2.093005957907768537e-05],{"arch":"sm_70","keys":["cuda","gpu"],"kind":"cuda","max_num_threads":1024,"max_shared_memory_per_block":65536,"max_threads_per_block":1024,"tag":"","thread_warp_size":32},[["TENSOR","float32",[1024,1024]],["TENSOR","float32",[512,2,1024]],["TENSOR","int32",[512,2]]]]]
[0,[[[["EnterPostproc",[],[],[]]],[]],[2.0366185720543149507e-05],{"arch":"sm_70","keys":["cuda","gpu"],"kind":"cuda","max_num_threads":1024,"max_shared_memory_per_block":65536,"max_threads_per_block":1024,"tag":"","thread_warp_size":32},[["TENSOR","float32",[1024,1024]],["TENSOR","float32",[512,2,1024]],["TENSOR","int32",[512,2]]]]]
[0,[[[["EnterPostproc",[],[],[]]],[]],[1.2903489240342233638e-05],{"arch":"sm_70","keys":["cuda","gpu"],"kind":"cuda","max_num_threads":1024,"max_shared_memory_per_block":65536,"max_threads_per_block":1024,"tag":"","thread_warp_size":32},[["TENSOR","float32",[1024,1024]],["TENSOR","float32",[512,2,1024]],["TENSOR","int32",[512,2]]]]]
[0,[[[["EnterPostproc",[],[],[]]],[]],[1.3138648684916798682e-05],{"arch":"sm_70","keys":["cuda","gpu"],"kind":"cuda","max_num_threads":1024,"max_shared_memory_per_block":65536,"max_threads_per_block":1024,"tag":"","thread_warp_size":32},[["TENSOR","float32",[1024,1024]],["TENSOR","float32",[512,2,1024]],["TENSOR","int32",[512,2]]]]]
[0,[[[["EnterPostproc",[],[],[]]],[]],[1.2918251263409876248e-05],{"arch":"sm_70","keys":["cuda","gpu"],"kind":"cuda","max_num_threads":1024,"max_shared_memory_per_block":65536,"max_threads_per_block":1024,"tag":"","thread_warp_size":32},[["TENSOR","float32",[1024,1024]],["TENSOR","float32",[512,2,1024]],["TENSOR","int32",[512,2]]]]]
[0,[[[["EnterPostproc",[],[],[]]],[]],[1.2881863691613128152e-05],{"arch":"sm_70","keys":["cuda","gpu"],"kind":"cuda","max_num_threads":1024,"max_shared_memory_per_block":65536,"max_threads_per_block":1024,"tag":"","thread_warp_size":32},[["TENSOR","float32",[1024,1024]],["TENSOR","float32",[512,2,1024]],["TENSOR","int32",[512,2]]]]]
[0,[[[["EnterPostproc",[],[],[]]],[]],[1.3201706402962159432e-05],{"arch":"sm_70","keys":["cuda","gpu"],"kind":"cuda","max_num_threads":1024,"max_shared_memory_per_block":65536,"max_threads_per_block":1024,"tag":"","thread_warp_size":32},[["TENSOR","float32",[1024,1024]],["TENSOR","float32",[512,2,1024]],["TENSOR","int32",[512,2]]]]]
[0,[[[["EnterPostproc",[],[],[]]],[]],[1.3186444413767717346e-05],{"arch":"sm_70","keys":["cuda","gpu"],"kind":"cuda","max_num_threads":1024,"max_shared_memory_per_block":65536,"max_threads_per_block":1024,"tag":"","thread_warp_size":32},[["TENSOR","float32",[1024,1024]],["TENSOR","float32",[512,2,1024]],["TENSOR","int32",[512,2]]]]]
[0,[[[["EnterPostproc",[],[],[]]],[]],[1.3158168751116668951e-05],{"arch":"sm_70","keys":["cuda","gpu"],"kind":"cuda","max_num_threads":1024,"max_shared_memory_per_block":65536,"max_threads_per_block":1024,"tag":"","thread_warp_size":32},[["TENSOR","float32",[1024,1024]],["TENSOR","float32",[512,2,1024]],["TENSOR","int32",[512,2]]]]]
[0,[[[["EnterPostproc",[],[],[]]],[]],[1.2883380772686434118e-05],{"arch":"sm_70","keys":["cuda","gpu"],"kind":"cuda","max_num_threads":1024,"max_shared_memory_per_block":65536,"max_threads_per_block":1024,"tag":"","thread_warp_size":32},[["TENSOR","float32",[1024,1024]],["TENSOR","float32",[512,2,1024]],["TENSOR","int32",[512,2]]]]]
[0,[[[["EnterPostproc",[],[],[]]],[]],[1.308903095365897417e-05],{"arch":"sm_70","keys":["cuda","gpu"],"kind":"cuda","max_num_threads":1024,"max_shared_memory_per_block":65536,"max_threads_per_block":1024,"tag":"","thread_warp_size":32},[["TENSOR","float32",[1024,1024]],["TENSOR","float32",[512,2,1024]],["TENSOR","int32",[512,2]]]]]
